Abhay_STT/__init__.py
Abhay_STT-0.1.dist-info/METADATA
Abhay_STT-0.1.dist-info/WHEEL
Abhay_STT-0.1.dist-info/top_level.txt
Abhay_STT-0.1.dist-info/RECORD
