Metadata-Version: 2.1
Name: Abhay-STT
Version: 0.1
Summary: A package to convert speech to text using selenium created by Abhay
Author: Abhay Agnihotri
Author-email: abhayagnihotri976@gmail.com
